steps_autoencoder/__init__.py
steps_autoencoder/data_generator.py
steps_autoencoder/experiment_tools.py
steps_autoencoder/models.py
tests/__init__.py
tests/test_autoencoder.py
steps_autoencoder-0.1.11.dist-info/LICENSE
steps_autoencoder-0.1.11.dist-info/METADATA
steps_autoencoder-0.1.11.dist-info/WHEEL
steps_autoencoder-0.1.11.dist-info/top_level.txt
steps_autoencoder-0.1.11.dist-info/RECORD
