Metadata-Version: 2.1
Name: steps-autoencoder
Version: 0.1.11
Summary: An Autoencoder for Steps Data
Home-page: https://github.com/Hekler-Designing-Health-Lab/steps-autoencoder
Author: Junghwan Park
Author-email: jup014@ucsd.edu
License-File: LICENSE
Requires-Dist: mlflow
Requires-Dist: neptune
Requires-Dist: numpy
Requires-Dist: pandas
Requires-Dist: ray
Requires-Dist: seaborn
Requires-Dist: setuptools
